pirateweather_translations/__init__.py
pirateweather_translations/dynamic_loader.py
pirateweather_translations/translation.py
pirateweather_translations/lang/__init__.py
pirateweather_translations/lang/ar.py
pirateweather_translations/lang/az.py
pirateweather_translations/lang/be.py
pirateweather_translations/lang/bg.py
pirateweather_translations/lang/bn.py
pirateweather_translations/lang/bs.py
pirateweather_translations/lang/ca.py
pirateweather_translations/lang/cs.py
pirateweather_translations/lang/cy.py
pirateweather_translations/lang/da.py
pirateweather_translations/lang/de.py
pirateweather_translations/lang/el.py
pirateweather_translations/lang/en.py
pirateweather_translations/lang/eo.py
pirateweather_translations/lang/es.py
pirateweather_translations/lang/et.py
pirateweather_translations/lang/fa.py
pirateweather_translations/lang/fi.py
pirateweather_translations/lang/fr.py
pirateweather_translations/lang/ga.py
pirateweather_translations/lang/gd.py
pirateweather_translations/lang/he.py
pirateweather_translations/lang/hi.py
pirateweather_translations/lang/hr.py
pirateweather_translations/lang/hu.py
pirateweather_translations/lang/id.py
pirateweather_translations/lang/is.py
pirateweather_translations/lang/it.py
pirateweather_translations/lang/ja.py
pirateweather_translations/lang/ka.py
pirateweather_translations/lang/kn.py
pirateweather_translations/lang/ko.py
pirateweather_translations/lang/kw.py
pirateweather_translations/lang/lv.py
pirateweather_translations/lang/ml.py
pirateweather_translations/lang/mr.py
pirateweather_translations/lang/nl.py
pirateweather_translations/lang/no.py
pirateweather_translations/lang/pa.py
pirateweather_translations/lang/pl.py
pirateweather_translations/lang/pt.py
pirateweather_translations/lang/ro.py
pirateweather_translations/lang/ru.py
pirateweather_translations/lang/sk.py
pirateweather_translations/lang/sl.py
pirateweather_translations/lang/sr.py
pirateweather_translations/lang/sv.py
pirateweather_translations/lang/ta.py
pirateweather_translations-1.3.0.dist-info/licenses/LICENSE
pirateweather_translations-1.3.0.dist-info/METADATA
pirateweather_translations-1.3.0.dist-info/WHEEL
pirateweather_translations-1.3.0.dist-info/top_level.txt
pirateweather_translations-1.3.0.dist-info/RECORD
