Metadata-Version: 2.4
Name: pirateweather-translations
Version: 1.3.0
Summary: Translate Pirate Weather API summaries into any language
Home-page: https://github.com/Pirate-Weather/translations
Download-URL: https://github.com/Pirate-Weather/translations/archive/1.3.0.tar.gz
Author: Pirate-Weather
License: BSD 2-clause
Keywords: weather API pirateweather translations
License-File: LICENSE
Dynamic: author
Dynamic: description
Dynamic: description-content-type
Dynamic: download-url
Dynamic: home-page
Dynamic: keywords
Dynamic: license
Dynamic: license-file
Dynamic: summary
